nectarine/__init__.py
nectarine/_utils.py
nectarine/configuration_provider.py
nectarine/dataclasses.py
nectarine/errors.py
nectarine/typing.py
nectarine/extensions/yaml.py
nectarine/providers/__init__.py
nectarine/providers/arguments.py
nectarine/providers/dictionary.py
nectarine/providers/env.py
nectarine/providers/json.py
nectarine-1.1.1.dist-info/LICENSE
nectarine-1.1.1.dist-info/METADATA
nectarine-1.1.1.dist-info/WHEEL
nectarine-1.1.1.dist-info/top_level.txt
nectarine-1.1.1.dist-info/RECORD
